check_keywords/__init__.py
check_keywords/check_keywords.py
pre_commit_keyword_checker-1.5.0.dist-info/LICENSE
pre_commit_keyword_checker-1.5.0.dist-info/METADATA
pre_commit_keyword_checker-1.5.0.dist-info/WHEEL
pre_commit_keyword_checker-1.5.0.dist-info/entry_points.txt
pre_commit_keyword_checker-1.5.0.dist-info/top_level.txt
pre_commit_keyword_checker-1.5.0.dist-info/RECORD
